dynamojo/__init__.py
dynamojo/base.py
dynamojo/config.py
dynamojo/exceptions.py
dynamojo/index.py
dynamojo/utils.py
dynamojo-1.1.6.dist-info/METADATA
dynamojo-1.1.6.dist-info/WHEEL
dynamojo-1.1.6.dist-info/RECORD
