Metadata-Version: 2.3
Name: Dynamojo
Version: 1.1.6
Summary: ORM For Dynamodb
Author: Mathew Moon
Author-email: me@mathewmoon.net
Requires-Python: >=3.12,<4.0
Classifier: Programming Language :: Python :: 3
Classifier: Programming Language :: Python :: 3.12
Classifier: Programming Language :: Python :: 3.13
Requires-Dist: boto3 (>=1.34.56,<2.0.0)
Requires-Dist: pydantic (>=2.0.0,<3.0.0)
Project-URL: Homepage, https://github.com/mathewmoon/dynamojo
Project-URL: Repository, https://github.com/mathewmoon/dynamojo
